{
    "normal":{
        "strong_against": ["None"],
        "weak_against": ["Rock", "Ghost", "Steel"],
        "resistant_to": ["Ghost"],
        "vulnerable_to": ["Fighting"]
    },
    "fighting":{
        "strong_against": ["Normal", "Rock", "Steel", "Ice", "Dark"],
        "weak_against": ["Flying", "Poison", "Psychic", "Bug", "Ghost", "Fairy"],
        "resistant_to": ["Rock", "Bug", "Dark"],
        "vulnerable_to": ["Flying", "Psychic", "Fairy"]
    },
    "flying":{
        "strong_against": ["Fighting", "Bug", "Grass"],
        "weak_against": ["Rock", "Steel", "Electric"],
        "resistant_to": ["Fighting", "Ground", "Bug", "Grass"],
        "vulnerable_to": ["Rock", "Electric", "Ice"]
    },
    "poison":{
        "strong_against": ["Grass", "Fairy"],
        "weak_against": ["Poison", "Ground", "Rock", "Ghost", "Steel"],
        "resistant_to": ["Fighting", "Poison", "Grass", "Fairy", "Bug"],
        "vulnerable_to": ["Ground", "Psychic"]
    },
    "ground":{
        "strong_against": ["Poison", "Rock", "Steel", "Fire", "Electric"],
        "weak_against": ["Flying", "Bug", "Grass"],
        "resistant_to": ["Poison", "Rock", "Electric"],
        "vulnerable_to": ["Water", "Grass", "Ice"]
    },
    "rock":{
        "strong_against": ["Flying", "Bug", "Fire", "Ice"],
        "weak_against": ["Fighting", "Ground", "Steel"],
        "resistant_to": ["Normal", "Flying", "Poison", "Fire"],
        "vulnerable_to": ["Fighting", "Ground", "Steel", "Water", "Grass"]
    },
    "bug":{
        "strong_against": ["Grass", "Psychic", "Dark"],
        "weak_against": ["Fighting", "Flying", "Poison", "Ghost", "Steel", "Fire", "Fairy"],
        "resistant_to": ["Fighting", "Ground", "Grass"],
        "vulnerable_to": ["Flying", "Rock", "Fire"]
    },
    "ghost":{
        "strong_against": ["Ghost", "Psychic"],
        "weak_against": ["Normal", "Dark"],
        "resistant_to": ["Normal", "Fighting", "Poison", "Bug"],
        "vulnerable_to": ["Ghost", "Dark"]
    },
    "steel":{
        "strong_against": ["Rock", "Ice", "Fairy"],
        "weak_against": ["Steel", "Fire", "Water", "Electric"],
        "resistant_to": ["Normal", "Flying", "Poison", "Rock", "Bug", "Steel", "Grass", "Psychic", "Ice", "Dragon", "Fairy"],
        "vulnerable_to": ["Fighting", "Ground", "Fire"]
    },
    "fire":{
        "strong_against": ["Bug", "Steel", "Grass", "Ice"],
        "weak_against": ["Rock", "Fire", "Water", "Dragon"],
        "resistant_to": ["Bug", "Steel", "Fire", "Grass", "Ice", "Fairy"],
        "vulnerable_to": ["Ground", "Rock", "Water"]
    },
    "water":{
        "strong_against": ["Ground", "Rock", "Fire"],
        "weak_against": ["Water", "Grass", "Dragon"],
        "resistant_to": ["Steel", "Fire", "Water", "Ice"],
        "vulnerable_to": ["Grass", "Electric"]
    },
    "grass":{
        "strong_against": ["Ground", "Rock", "Water"],
        "weak_against": ["Flying", "Poison", "Bug", "Steel", "Fire", "Grass", "Dragon"],
        "resistant_to": ["Ground", "Water", "Grass", "Electric"],
        "vulnerable_to": ["Flying", "Poison", "Bug", "Fire", "Ice"]
    },
    "electric":{
        "strong_against": ["Flying", "Water"],
        "weak_against": ["Ground", "Grass", "Electric", "Dragon"],
        "resistant_to": ["Flying", "Steel", "Electric"],
        "vulnerable_to": ["Ground"]
    },
    "psychic":{
        "strong_against": ["Fighting", "Poison"],
        "weak_against": ["Steel", "Psychic", "Dark"],
        "resistant_to": ["Fighting", "Psychic"],
        "vulnerable_to": ["Bug", "Ghost", "Dark"]
    },
    "ice":{
        "strong_against": ["Flying", "Ground", "Grass", "Dragon"],
        "weak_against": ["Steel", "Fire", "Water", "Ice"],
        "resistant_to": ["Ice"],
        "vulnerable_to": ["Fighting", "Rock", "Steel", "Fire"]
    },
    "dragon":{
        "strong_against": ["Dragon"],
        "weak_against": ["Steel", "Fairy"],
        "resistant_to": ["Fire", "Water", "Grass", "Electric"],
        "vulnerable_to": ["Ice", "Dragon", "Fairy"]
    },
    "fairy":{
        "strong_against": ["Fighting", "Dragon", "Dark"],
        "weak_against": ["Poison", "Steel", "Fire"],
        "resistant_to": ["Fighting", "Bug", "Dragon", "Dark"],
        "vulnerable_to": ["Poison", "Steel"]
    },
    "dark":{
        "strong_against": ["Ghost", "Psychic"],
        "weak_against": ["Fighting", "Dark", "Fairy"],
        "resistant_to": ["Ghost", "Psychic", "Dark"],
        "vulnerable_to": ["Fighting", "Bug", "Fairy"]
    }
}
